{"date":"2026-10-25","v":1,"sets":{"easy":{"name":"Sunday Drive","par":24,"holes":[{"plate":"ERE","par":4,"ex":"here","birdie":null},{"plate":"DIT","par":4,"ex":"edit","birdie":null},{"plate":"FOT","par":4,"ex":"foot","birdie":null},{"plate":"TNE","par":4,"ex":"tune","birdie":null},{"plate":"ART","par":4,"ex":"part","birdie":null},{"plate":"SOR","par":4,"ex":"sort","birdie":null}]},"medium":{"name":"Cross Country","par":27,"holes":[{"plate":"VRY","par":4,"ex":"vary","birdie":null},{"plate":"EIT","par":4,"ex":"edit","birdie":null},{"plate":"HAE","par":4,"ex":"hate","birdie":null},{"plate":"ALR","par":5,"ex":"alarm","birdie":4},{"plate":"PHS","par":5,"ex":"phase","birdie":4},{"plate":"CLR","par":5,"ex":"clear","birdie":null}]},"hard":{"name":"Rally Stage","par":32,"holes":[{"plate":"QUE","par":5,"ex":"queue","birdie":4},{"plate":"DRS","par":5,"ex":"doors","birdie":4},{"plate":"TEH","par":5,"ex":"teach","birdie":4},{"plate":"WHL","par":5,"ex":"wheel","birdie":null},{"plate":"RPA","par":6,"ex":"repair","birdie":5},{"plate":"EOT","par":6,"ex":"devote","birdie":5}]}}}