{"date":"2026-10-20","v":1,"n":150,"sets":{"easy":[["dated","hirdly"],["miles","vutes"],["argues","traly"],["works","fenger"],["fight","wehel"],["tracks","sived"],["signs","raect"],["editor","wroks"],["raises","imopse"],["brown","sefety"],["grind","celar"],["seven","tocket"],["adjust","fammily"],["states","spere"],["gotten","adipts"],["double","psases"],["doubt","scrupt"],["script","murely"],["today","chack"],["faster","appoar"],["cursor","hury"],["award","betes"],["feeds","remmark"],["truly","anual"],["driver","wirte"],["stands","thruw"],["honest","storng"],["amused","spirrit"],["bucket","tusts"],["edited","soved"],["lasts","edutor"],["really","calims"],["quits","bosing"],["heart","nedes"],["ensure","golbal"],["worked","duoble"],["knows","mirely"],["affair","publac"],["noting","foncy"],["sought","digtis"],["truly","munths"],["leaves","isued"],["scrap","kepes"],["picked","alram"],["write","sived"],["listen","suonds"],["dealt","flaed"],["famous","yaers"],["buying","skoll"],["sites","froces"],["crazy","diggits"],["traps","pocekt"],["ticket","kniwn"],["paying","thonks"],["behave","tomed"],["prefer","coeple"],["names","affurd"],["prove","rusort"],["amuse","toech"],["reach","farme"],["rooms","tuday"],["issues","perts"],["three","brone"],["reads","warth"],["fixed","knick"],["output","cuont"],["ideas","franch"],["derive","ruach"],["attend","funy"],["knocks","rufer"],["sugar","likkely"],["accord","cises"],["strict","leoks"],["modify","leeves"],["labels","selly"],["funny","breoch"],["elect","soccial"],["magic","flaes"],["fields","silves"],["grave","wrold"],["badly","coent"],["number","rever"],["valid","inpat"],["coded","gruph"],["apple","bleck"],["posts","tulls"],["prompt","bulids"],["occur","crissis"],["waited","degere"],["prime","labbels"],["nasty","palce"],["begin","palin"],["women","bluck"],["amount","yeirs"],["watch","cuver"],["force","mestly"],["prone","thangs"],["breach","truin"],["number","squrae"],["hides","fexes"],["truly","pharse"],["teach","nomed"],["chaos","plunt"],["supply","trush"],["charge","sekes"],["demand","snese"],["stuff","exasts"],["easier","herreby"],["liking","bigan"],["basing","sacond"],["output","bigin"],["cursor","exucse"],["finish","veried"],["kinds","metol"],["fries","loked"],["awake","taeght"],["owing","strock"],["moving","lench"],["paying","anyawy"],["biting","loghts"],["asleep","botes"],["school","logac"],["breaks","mether"],["trusts","lanked"],["learn","ocur"],["smile","meral"],["deduce","coiped"],["walked","knucks"],["manner","feelds"],["retain","laber"],["comes","valume"],["worst","errirs"],["claim","mands"],["posts","smaple"],["normal","cleon"],["heard","attond"],["images","seing"],["whilst","asliep"],["heads","trests"],["trains","colur"],["faith","brokken"],["local","coipes"],["update","perfer"],["earth","poshes"],["price","shats"],["define","deluy"],["trains","easuly"],["route","loaks"],["thanks","gronud"],["loudly","gemes"]],"medium":[["disease","gianing"],["terminate","intonded"],["talked","eviddently"],["accent","ductors"],["parent","rumros"],["versatile","wroldwide"],["consulting","superivses"],["adjusts","meiting"],["ignorant","inerita"],["hinting","mannager"],["writings","jaming"],["persist","empolying"],["became","importunt"],["slogan","obtaoning"],["corrupting","forguve"],["pretends","decilned"],["misprint","wastern"],["optical","simplistoc"],["unlikely","evalved"],["natives","inspocts"],["retain","confese"],["technique","breoch"],["interfere","primpt"],["supporters","horitage"],["refusing","maping"],["prospects","progremmer"],["rising","vagguely"],["underlay","hindful"],["choral","signels"],["moving","berath"],["furthest","conection"],["plastering","bargian"],["greedy","commited"],["bookstore","dominoted"],["revenue","appeils"],["element","exahusts"],["monster","gronted"],["purple","ovrenight"],["household","complaecnt"],["convert","inocme"],["parsed","tuctless"],["inspection","sunirse"],["inferior","roated"],["breathed","integartes"],["punished","idontify"],["judging","slidding"],["abolition","drevers"],["repeatedly","exicted"],["phones","suppossed"],["generous","lutters"],["frustrated","distonces"],["addictive","numerrous"],["impair","therreby"],["tables","injusitce"],["estimate","tracced"],["willing","mechansims"],["typesets","kniwledge"],["findings","unruadable"],["comprises","aboslute"],["juvenile","coloing"],["uncertain","vuriation"],["formation","conodne"],["project","boged"],["taxation","functoined"],["hereby","oblege"],["conscience","presumming"],["underlies","inhabtied"],["omissions","excase"],["counseled","prefered"],["implements","evudently"],["popularity","spensors"],["express","unablanced"],["infamous","miselading"],["lighting","punsihment"],["strongly","resotres"],["length","munned"],["converts","muters"],["promptly","brewsed"],["murdering","unleck"],["naughty","handiccap"],["shakes","flelows"],["rolled","foerth"],["opinion","golves"],["dreams","symbil"],["symphony","glunce"],["deducing","dispusing"],["influences","milecules"],["dubious","oirented"],["recipient","mottives"],["weekday","varaince"],["speaking","deting"],["infinity","divune"],["recovery","brungs"],["pizzas","paonfully"],["controlled","apearance"],["processed","impalse"],["scratches","recceive"],["develop","cabunet"],["assemble","bleses"],["manager","skepticcal"],["corrupts","assosting"],["despite","murging"],["deserving","emmerging"],["vigorously","cheldish"],["consulted","necussary"],["mobile","sohots"],["suspected","holuday"],["guards","conector"],["crossroads","sigantures"],["descend","convirting"],["directions","illeagl"],["injustice","misleid"],["considers","dictattor"],["necessity","mengles"],["virtually","fereways"],["forcibly","stirve"],["absent","crewding"],["manually","presed"],["proposed","parites"],["urgently","versatlie"],["ancestors","transofrm"],["exited","pormoting"],["graffiti","recokn"],["inclined","jomping"],["policies","retreived"],["marrying","picutre"],["contain","redduction"],["overpriced","evoletion"],["minding","leuning"],["orthodox","attitdues"],["circuitry","schulars"],["lining","missuse"],["composing","saddenned"],["nowhere","expolde"],["glowing","propposing"],["meantime","timascale"],["sacked","jackots"],["birthday","leglaly"],["engages","redduce"],["measured","animmal"],["canonical","aliance"],["bidding","repurter"],["afternoons","contuin"],["shocks","presuades"],["aardvark","ressumed"],["electrical","botting"],["advertise","invalud"],["integrity","revlot"],["semantics","cilmate"],["prizes","inhabated"]],"hard":[["invigorates","restufller"],["corroborate","improbbably"],["trigonometry","complexuty"],["gratifications","availabbility"],["eyeballing","anticippates"],["predictions","assoication"],["precedents","beatuifying"],["reflection","resturcture"],["archipelagos","asceratined"],["stubbornest","optomitrist"],["properties","cloadburst"],["concentrations","dustributor"],["inundation","camuoflage"],["canvassers","improbabbility"],["incinerators","illitarates"],["sprinkling","disaprages"],["convoluted","occarrence"],["incinerator","appliccation"],["specifications","bankrapting"],["goalkeepers","exterminnated"],["biologically","compossition"],["condominiums","unnattainable"],["acknowledgment","overruning"],["sepulchers","sturctures"],["realistically","departmenatl"],["chiropractor","inidcations"],["regimenting","incidintally"],["vocational","substittutes"],["incongruous","frofeiting"],["ophthalmology","reifnement"],["scientists","unscaentific"],["overburdens","prodductions"],["grasshopper","sociologgical"],["insensitivity","copullation"],["postmaster","initmation"],["abominable","aclimatizes"],["commemoration","conoisseur"],["perfecting","scrutinezing"],["transliteration","incorpoarting"],["jettisoned","meldoramatic"],["irresponsible","candidaccies"],["semicolons","emphassized"],["hitchhiker","dascounted"],["configuring","impassinoed"],["salespersons","atachments"],["millionaire","horrendoas"],["discharges","misjedging"],["flustering","discourtosy"],["derivatives","exaspurates"],["liturgical","mutilatting"],["acknowledge","transmiting"],["apparition","anachronsims"],["computational","mainfestations"],["rectangles","friondliness"],["nonentities","silohuetting"],["hemisphere","extraddition"],["televisions","comparattives"],["equestrian","corpsucles"],["indication","fastennings"],["incidences","shaddowiest"],["disparages","physiologiccal"],["thoughtlessly","redresing"],["supervised","unstetling"],["temperaments","obliggations"],["locomotion","broadcsats"],["southeastern","transatlanitc"],["waterworks","liqudiation"],["challenges","subverisve"],["concentrated","restfuler"],["fumigation","condittioning"],["autocratic","seducitons"],["legislature","represions"],["dissociated","ovrecrowded"],["leapfrogged","inudcements"],["competitive","adjastments"],["hospitalized","scrapbokos"],["illuminations","rellinquishing"],["iridescent","belabiring"],["emphasizing","remissoins"],["supportive","adloescence"],["unintended","exonnerated"],["expressing","equastrian"],["summonsing","fashinoably"],["terminally","impratially"],["grandstanded","transalted"],["humiliates","evollutionary"],["importance","rellinquishes"],["voluptuous","remiburses"],["considerate","commissinoing"],["oppressing","rudefining"],["indefinable","briddesmaid"],["paradoxical","longshormeen"],["jackknives","inedpendently"],["upholstering","ameprsands"],["capitulating","comercials"],["bewildering","imaignations"],["disconcerts","roprograms"],["commencing","inappropruate"],["mayonnaise","adventering"],["installment","withdarwing"],["pretensions","supersenic"],["rationalizing","enshrinning"],["freshening","horseraddish"],["pleasuring","fruloughing"],["comparatives","archaeloogy"],["roadblocking","mistakunly"],["reschedule","witnesing"],["loudspeaker","liquidtaing"],["inadvertent","marketpalce"],["unburdened","unilaterel"],["disembarked","exponnentially"],["impossibly","reciporcals"],["carpentered","gadparents"],["inquisitions","oversteping"],["kitchenettes","sugestion"],["nineteenth","expeddiency"],["sandstorms","dishawsher"],["instantaneously","otudistances"],["clarification","cintralizing"],["intangible","soundprofing"],["newsletters","disopsables"],["disgusting","ratienality"],["comprehended","insinauting"],["polarization","doplication"],["afterwards","deomlishes"],["aristocracy","afiliated"],["capabilities","compensatted"],["masqueraded","bulfighter"],["fulfilling","fedrealism"],["vandalizing","comending"],["discovering","formulattes"],["consonants","riccocheted"],["barricades","carictauring"],["fortunately","marshamllow"],["tenderizing","landolcked"],["hallmarked","haoghtiest"],["headstrong","adventurring"],["replacement","starightening"],["forearming","arbitartes"],["terminologies","cumpulsive"],["dislocations","boradsides"],["examination","devellopment"],["hinterland","noiselissly"],["delinquents","inidgestible"],["squeakiest","aclimates"],["disregards","misgoiding"],["chickening","pigybacking"],["battlefields","prevneting"],["thereafter","dormitorries"],["conspicuous","alturnative"]]}}