{"date":"2026-09-25","v":1,"n":150,"sets":{"easy":[["divide","pyaing"],["occurs","favar"],["trial","wals"],["quits","buhave"],["driver","noive"],["awful","anyawy"],["white","nuise"],["amused","wrothy"],["alive","cofefe"],["tasks","nattion"],["around","puwers"],["loudly","pirme"],["falls","derrive"],["virtue","focts"],["grants","qaick"],["paper","trist"],["unlike","loter"],["metal","sodes"],["fewest","cuonty"],["count","recrod"],["arises","hitel"],["leader","ceurt"],["market","fally"],["pretty","porves"],["trunk","arround"],["agreed","bassing"],["joined","ocurs"],["fields","lattest"],["print","sperad"],["grind","werds"],["borne","metter"],["walks","rotue"],["think","linch"],["pages","froce"],["light","suger"],["begun","lught"],["proved","wirtes"],["inner","leves"],["leads","honts"],["leaves","ciding"],["chosen","meuth"],["argued","mether"],["wills","revael"],["shops","merrits"],["vastly","maent"],["split","prunt"],["areas","takking"],["formed","yuong"],["using","honds"],["finger","hirses"],["almost","neisy"],["digits","bicket"],["expert","collors"],["indeed","makking"],["passes","liaved"],["volume","permot"],["pushes","amoont"],["agree","fromer"],["syntax","morks"],["closes","saont"],["tested","annays"],["papers","borad"],["stayed","immages"],["purely","pyaing"],["count","toduy"],["handy","admots"],["water","cilled"],["unique","begen"],["easily","pelled"],["needs","womin"],["struck","valed"],["strict","trush"],["grown","remrak"],["crash","unbale"],["alive","nirth"],["stuff","degit"],["falls","foregt"],["stood","morch"],["object","cerdit"],["dated","metohd"],["noise","colros"],["worthy","simle"],["social","flosh"],["coffee","pleuse"],["hurry","loks"],["lucky","biref"],["wider","tonks"],["spends","dorve"],["became","gless"],["dollar","prive"],["sells","omtis"],["strict","optuon"],["matter","ensare"],["handle","rughts"],["nation","unluke"],["place","arive"],["belong","groops"],["stuff","digtis"],["enable","cheld"],["scrap","prety"],["paying","boaght"],["media","knecks"],["twelve","asede"],["elects","whel"],["crisis","piople"],["rates","cluss"],["chips","seasun"],["secure","suden"],["person","asusme"],["terms","waight"],["fourth","amied"],["looks","upsats"],["double","sapce"],["proves","subest"],["fallen","gruwth"],["plots","putrol"],["column","twanty"],["vector","satte"],["backed","boting"],["second","fruely"],["ditto","cuding"],["keeps","crish"],["stock","iduas"],["manage","suzes"],["option","hippen"],["crazy","qiuck"],["honest","accuss"],["shoot","weder"],["budget","tupes"],["coffee","daffer"],["dozen","maent"],["upset","sepak"],["fully","inpets"],["values","schume"],["review","untis"],["landed","filse"],["french","asode"],["lasts","decnet"],["clock","sheps"],["discs","saffely"],["hurry","reatin"],["guard","leser"],["remark","soith"],["messy","hurdly"],["shown","hepes"],["pushes","ownig"],["bright","ownig"],["closes","seccond"],["avoids","habbits"],["avoids","braech"]],"medium":[["dishes","explere"],["farewell","varries"],["diesel","monotor"],["eleven","regoins"],["detection","tarced"],["windows","ancinet"],["dedicating","tuoches"],["verify","triveal"],["seemingly","attock"],["friendship","asisting"],["houses","hagher"],["economy","wonderred"],["theology","refote"],["smiling","chorral"],["forgiving","ancestirs"],["involved","creatvie"],["raving","fromatted"],["hinting","fashoins"],["different","desserted"],["thereafter","atheasm"],["defects","opressing"],["scatter","giuding"],["unpopular","jionts"],["porters","moldly"],["patching","accont"],["bastards","craetor"],["concerts","develaped"],["empties","ciptured"],["represent","premmises"],["warranty","databbases"],["horizon","rasponding"],["reliably","manding"],["shifting","mesters"],["pedantic","siutating"],["plural","loacting"],["operations","sniking"],["statement","berred"],["playground","comopses"],["outgoing","broguht"],["rectifies","moddest"],["amplifier","exhausteve"],["gossip","witnesed"],["audiences","prelong"],["fainter","biffer"],["marriage","intind"],["carries","liasion"],["comparable","postopne"],["ridding","dedaline"],["stuffing","winduw"],["suspension","divreted"],["wisest","drofts"],["choosing","electroinc"],["smoker","shalves"],["rereads","stucks"],["noticing","devellop"],["informal","herting"],["square","wareohuse"],["preferred","halder"],["cluster","objecitve"],["notably","stratled"],["dealing","vectars"],["picture","hapily"],["literature","todying"],["obtain","raecting"],["scoring","convorter"],["executable","arrising"],["promoted","pelasure"],["crimes","nottifies"],["choosing","repiled"],["ranted","dustort"],["picture","engiener"],["character","polituness"],["outraged","ferely"],["washing","sintenced"],["conducted","officilas"],["derange","citching"],["identify","acceunt"],["grants","alolwing"],["pointed","schedole"],["rounding","comming"],["misguided","selver"],["payment","lingeistic"],["unnatural","gloirous"],["solves","withdriws"],["therapy","lumiting"],["illustrate","smoshed"],["algorithm","giaring"],["dollar","tarcing"],["handicap","bocycle"],["pompous","revaew"],["diagnosis","puases"],["cheats","creoture"],["learns","slawed"],["lunatic","ceties"],["precedes","jongle"],["surprising","letaher"],["incoherent","licnesing"],["percent","davided"],["insects","subtelties"],["mirrors","infarm"],["carrots","hespitals"],["voices","reggain"],["interval","stapped"],["cyclist","peotic"],["enjoyment","refinnes"],["shelves","diagonsis"],["factor","crosing"],["thirst","queting"],["degenerate","liasion"],["gathers","loodest"],["elevator","orgainzers"],["corridor","praked"],["stroke","withdarwn"],["remarks","arugable"],["sneaked","letaher"],["loudly","rasked"],["resolution","bufferring"],["defines","ovorcome"],["records","guording"],["converts","bufering"],["partially","bigest"],["results","curriosity"],["unlimited","divoting"],["impressing","mothods"],["elevators","colorred"],["deduction","pruvide"],["reckoning","factaul"],["violate","cloims"],["crashing","portotype"],["addressing","prampting"],["mistook","novilty"],["transition","reanstates"],["punishment","transcrapt"],["revises","taxtbooks"],["severe","definnite"],["spoiled","errurs"],["hasten","mirking"],["adjusted","renwes"],["splitting","adivsor"],["observe","pruced"],["transfer","intenisve"],["offender","contorller"],["hospital","laegue"],["provoke","entatles"],["teaches","colapses"],["declined","slopy"],["browse","cincede"],["summarized","pratially"],["eating","snigular"],["overheads","assurred"]],"hard":[["symptomatic","atracting"],["reallocate","fragmantary"],["calibrations","atracting"],["flavorings","curriuclum"],["proletarians","toppography"],["microwaves","demnostrating"],["orchestrate","impessable"],["modernizing","microffilming"],["unsuitable","eavluations"],["procession","cordinating"],["contradictory","unscrupullous"],["picturesque","inumerable"],["impregnating","consonnants"],["reformation","innumerrable"],["magnificent","appropirate"],["reflective","turnatbles"],["insurances","trappezoids"],["collisions","tombsotnes"],["stethoscope","expereinces"],["departures","genirosities"],["distillers","prefferable"],["illustrate","dismebarking"],["stagnation","descriptros"],["deprivation","expictations"],["horseradishes","emancipatting"],["scientific","resollutions"],["inaccessible","condascended"],["misinforming","permisible"],["repeatable","indicattors"],["breadwinner","undregrowth"],["flimsiness","clumisness"],["persecutions","duclension"],["longshoremen","redoctions"],["acceptances","empolyment"],["infections","lumminaries"],["segmenting","occassioned"],["immorality","haedstones"],["cornflakes","antisecial"],["photocopying","transacitons"],["homosexuals","tarditional"],["distributes","accummodations"],["economical","surcahrging"],["authorities","circumefrences"],["commercialism","slandoring"],["assassinate","sacrilgees"],["systematically","intenisties"],["penthouses","ocupations"],["efficiencies","contmeptible"],["disjointing","advenutrous"],["constitution","ventulators"],["neglectful","veewpoints"],["offensives","satbilizing"],["acclimatize","calculatros"],["overlapping","delbierations"],["magnanimous","metohdology"],["lamentation","transluccent"],["ragamuffin","merchanidsing"],["principalities","standaridze"],["pinpointing","illustraitve"],["unassuming","undertikes"],["dissociating","disciplinned"],["disentangles","refrsehment"],["academically","colloquilaism"],["overpasses","ocasioning"],["discomforting","irationals"],["vanquished","stradling"],["annotation","qualfiying"],["contradictory","subordinetes"],["restrictive","cultiavting"],["psychiatric","adventorers"],["radioactivity","tranquelized"],["inaccuracy","ragamufin"],["autographed","whitiwashes"],["theologies","acompanist"],["blackboard","astersiked"],["intelligently","stommaching"],["municipalities","compratment"],["undertones","mouthpaece"],["technology","replecating"],["championship","ilustrator"],["irregularity","preddictably"],["librarians","intertiwne"],["glamorized","advanatged"],["subsidized","bloeprints"],["reinstates","discahrges"],["irregulars","gymnastcis"],["salespersons","negliggently"],["maintained","scatering"],["contributing","anoyingly"],["relinquishing","wherrewithal"],["unthinkable","prepetually"],["inaccessible","exclumation"],["plantations","extartionate"],["crystallizing","sommersaults"],["newscasters","nunconformist"],["connectivity","undersudes"],["sisterhood","spensorship"],["civilizing","frowardest"],["upholsterers","indivadualism"],["toothpastes","commandering"],["mascaraing","falseohods"],["forewarning","demonstartive"],["supplement","popullarizes"],["pitchforking","encompased"],["demonstrates","proficciently"],["contaminating","reinsatting"],["consortium","rendezveus"],["understands","suplement"],["unpopularity","delicatesens"],["bookkeepers","communnicator"],["supplementary","nonchalunt"],["orientations","curtianing"],["unforgettable","conections"],["cheerfulness","descriminated"],["transforms","proclamied"],["enumerated","distursted"],["agnosticism","dressamkers"],["auxiliaries","thoruoghfares"],["inappropriate","menimizing"],["surfboards","obstrections"],["substitution","chompionships"],["assailants","momnetarily"],["conventionally","hypirtension"],["similarity","ingeinously"],["occupations","mesmanagement"],["upbringing","femiliarize"],["splendidest","inidcation"],["indisputable","phiolsophers"],["permitting","spindloest"],["undetected","pleyhouses"],["projectile","recpetacle"],["impositions","considerrably"],["tobogganing","leapfroged"],["spattering","hitchiked"],["landscaping","manipullate"],["precarious","inahbiting"],["horizontal","shuplifters"],["rechargeable","vagbaonded"],["sanctified","claibrates"],["dispensary","aninhilated"],["university","jeurneying"],["partiality","scappegoated"],["atmospheric","witnassing"],["overbearing","asignment"],["distressingly","incapacittae"],["disparaged","redajusted"],["segmenting","froeground"],["constructed","resiarcher"],["redirection","haevenlier"],["fundamental","rhetoircal"]]}}