{"date":"2026-08-26","v":1,"sets":{"easy":{"site":"Cottage","hand":["c","f","g","h","l","m","n","t"],"gravity":2,"par":20,"stories":4,"floors":[{"left":"T","right":"L","word":"technical","width":9},{"left":"C","right":"G","word":"counting","width":8},{"left":"F","right":"N","word":"function","width":8},{"left":"M","right":"H","word":"mammoth","width":7}]},"medium":{"site":"Townhouse","hand":["b","c","f","h","m","n","p","r","s","t"],"gravity":2,"par":24,"stories":4,"floors":[{"left":"C","right":"M","word":"criticism","width":9},{"left":"F","right":"S","word":"functions","width":9},{"left":"P","right":"T","word":"permanent","width":9},{"left":"R","right":"N","word":"reception","width":9}]},"hard":{"site":"Tower Block","hand":["b","c","d","f","g","h","l","r","s","t","x","y"],"gravity":1,"par":34,"stories":5,"floors":[{"left":"B","right":"L","word":"beautiful","width":9},{"left":"D","right":"T","word":"difficult","width":9},{"left":"G","right":"Y","word":"gradually","width":9},{"left":"S","right":"C","word":"statistic","width":9},{"left":"R","right":"H","word":"research","width":8}]}}}