{"date":"2026-08-04","v":1,"sets":{"easy":{"site":"Cottage","hand":["b","f","h","l","n","r","s","t"],"gravity":2,"par":21,"stories":4,"floors":[{"left":"B","right":"L","word":"beautiful","width":9},{"left":"S","right":"N","word":"situation","width":9},{"left":"T","right":"R","word":"transfer","width":8},{"left":"H","right":"F","word":"herself","width":7}]},"medium":{"site":"Townhouse","hand":["b","c","g","h","l","m","n","r","s","t"],"gravity":2,"par":24,"stories":4,"floors":[{"left":"B","right":"G","word":"bothering","width":9},{"left":"C","right":"M","word":"criticism","width":9},{"left":"N","right":"L","word":"numerical","width":9},{"left":"R","right":"S","word":"restricts","width":9}]},"hard":{"site":"Tower Block","hand":["c","d","f","g","h","k","m","n","s","t","v","w"],"gravity":1,"par":35,"stories":6,"floors":[{"left":"C","right":"T","word":"confident","width":9},{"left":"M","right":"D","word":"mentioned","width":9},{"left":"V","right":"S","word":"vacations","width":9},{"left":"F","right":"N","word":"function","width":8},{"left":"K","right":"G","word":"knocking","width":8},{"left":"H","right":"W","word":"hacksaw","width":7}]}}}